.gitignore
LICENSE
README.md
Tests.py
local-config.yml
requirements.txt
setup.cfg
setup.py
api/resource/application-local.yml
api/resource/application.yml
python_helper/__init__.py
python_helper.egg-info/PKG-INFO
python_helper.egg-info/SOURCES.txt
python_helper.egg-info/dependency_links.txt
python_helper.egg-info/requires.txt
python_helper.egg-info/top_level.txt
python_helper/api/src/annotation/EnumAnnotation.py
python_helper/api/src/annotation/EnvironmentAnnotation.py
python_helper/api/src/annotation/MethodAnnotation.py
python_helper/api/src/annotation/TestAnnotation.py
python_helper/api/src/domain/Constant.py
python_helper/api/src/domain/FileOperation.py
python_helper/api/src/helper/LogHelperHelper.py
python_helper/api/src/helper/ObjectHelperHelper.py
python_helper/api/src/helper/RandomHelperHelper.py
python_helper/api/src/helper/SettingHelperHelper.py
python_helper/api/src/helper/StringHelperHelper.py
python_helper/api/src/service/DateTimeHelper.py
python_helper/api/src/service/EnvironmentHelper.py
python_helper/api/src/service/FileHelper.py
python_helper/api/src/service/LogHelper.py
python_helper/api/src/service/ObjectHelper.py
python_helper/api/src/service/RandomHelper.py
python_helper/api/src/service/ReflectionHelper.py
python_helper/api/src/service/SettingHelper.py
python_helper/api/src/service/StringHelper.py
python_helper/api/src/service/TestHelper.py
python_helper/api/test/api/resource/application-circular-reference.yml
python_helper/api/test/api/resource/application-local.yml
python_helper/api/test/api/resource/application.yml
python_helper/api/test/api/resource/boolean-application-local.yml
python_helper/api/test/api/resource/boolean-application.yml
python_helper/api/test/api/resource/fallback-application.yml
python_helper/api/test/api/resource/fallback-priority-local.yml
python_helper/api/test/api/resource/fallback-priority.yml
python_helper/api/test/api/resource/framework.yml
python_helper/api/test/api/resource/other-application-local.yml
python_helper/api/test/api/resource/other-application.yml
python_helper/api/test/api/resource/referencing-fallback-application.yml
