Metadata-Version: 2.1
Name: python-helper
Version: 0.3.74
Summary: python helper package
Home-page: https://github.com/SamuelJansen/python-helper/
Download-URL: https://github.com/SamuelJansen/python-helper/archive/v0.3.74.tar.gz
Author: Samuel Jansen
Author-email: samuel.jansenn@gmail.com
License: MIT
Keywords: helper,python helper package,python helper,helper package
Classifier: Development Status :: 3 - Alpha
Classifier: Intended Audience :: Developers
Classifier: Topic :: Software Development :: Build Tools
Classifier: License :: OSI Approved :: MIT License
Classifier: Programming Language :: Python :: 3.7
Requires-Python: >=3.7
License-File: LICENSE
